{
  "hash": "38f8ef4b",
  "browserHash": "2a5d91d0",
  "optimized": {
    "react/jsx-dev-runtime": {
      "src": "../../node_modules/react/jsx-dev-runtime.js",
      "file": "react_jsx-dev-runtime.js",
      "fileHash": "dc70c60b",
      "needsInterop": true
    },
    "react": {
      "src": "../../node_modules/react/index.js",
      "file": "react.js",
      "fileHash": "32845ede",
      "needsInterop": true
    },
    "react-dom/client": {
      "src": "../../node_modules/react-dom/client.js",
      "file": "react-dom_client.js",
      "fileHash": "dfdbaf6d",
      "needsInterop": true
    },
    "react-redux": {
      "src": "../../node_modules/react-redux/es/index.js",
      "file": "react-redux.js",
      "fileHash": "ac900e66",
      "needsInterop": false
    },
    "@reduxjs/toolkit": {
      "src": "../../node_modules/@reduxjs/toolkit/dist/redux-toolkit.esm.js",
      "file": "@reduxjs_toolkit.js",
      "fileHash": "b205628c",
      "needsInterop": false
    }
  },
  "chunks": {
    "chunk-DZXRV6RW": {
      "file": "chunk-DZXRV6RW.js"
    },
    "chunk-ZAUFE7H7": {
      "file": "chunk-ZAUFE7H7.js"
    },
    "chunk-UXIASGQL": {
      "file": "chunk-UXIASGQL.js"
    }
  }
}